[
  {
    "teacher": "Олена Іваненко",
    "date": "2026-04-11",
    "time": "08:00",
    "duration": 60
  },
  {
    "teacher": "Олена Іваненко",
    "date": "2026-04-28",
    "time": "08:00",
    "duration": 120
  },
  {
    "teacher": "Олена Іваненко",
    "date": "2026-05-11",
    "time": "08:00",
    "duration": 60
  },
  {
    "teacher": "Олена Іваненко",
    "date": "2026-05-24",
    "time": "11:00",
    "duration": 60
  },
  {
    "teacher": "Наталія Бондар",
    "date": "2026-05-26",
    "time": "08:30",
    "duration": 120
  }
]